RobotNotifications/__init__.py
robotframework_notifications-1.2.0.dist-info/METADATA
robotframework_notifications-1.2.0.dist-info/WHEEL
robotframework_notifications-1.2.0.dist-info/top_level.txt
robotframework_notifications-1.2.0.dist-info/RECORD
