Metadata-Version: 2.1
Name: robotframework-notifications
Version: 1.2.0
Summary: Send notifications to Slack or Mattermost using Robot Framework.
Home-page: https://github.com/tlolkema/RobotNotifications
Author: Tim Lolkema
Author-email: tim@detesters.nl
License: MIT
Platform: UNKNOWN
Classifier: License :: OSI Approved :: MIT License
Classifier: Programming Language :: Python :: 3
Classifier: Programming Language :: Python :: 3.6
Classifier: Programming Language :: Python :: 3.7
Classifier: Programming Language :: Python :: 3.8
Requires-Dist: requests
